Elementary Gates/Mux.vhdl
library IEEE;
use IEEE.std_logic_1164.all;


entity MUX is
	port(
		a_i, b_i, sel: in std_logic;
		z_o 	   			: out std_logic
		);
end MUX;


architecture rtl of MUX is
	signal sel_inv, st1_0, st1_1 :std_logic;
	
	begin
		sel_inv <= sel nand sel;
		st1_0 <= a_i nand sel_inv;
		st1_1 <= b_i nand sel;
		z_o <= st1_0 nand st1_1;
end rtl;

Elementary Gates/MuxTB.vhdl
library IEEE;
use IEEE.std_logic_1164.all;


entity MUX_tb is
end MUX_tb;


architecture behavioural of MUX_tb is
	signal a_i, b_i, sel : std_logic := '0';
	signal z_o 	  		 : std_logic;
	
	begin
		UUT : entity work.MUX port map(
			a_i => a_i, b_i => b_i, sel => sel, z_o => z_o
			);
			
	    process begin
			a_i <= '0';
			b_i <= '0';
			sel <= '0';
			wait for 1 ns;
	
			b_i <= '1';
			wait for 1 ns;
			
			a_i <= '1';
			b_i <= '0';
			wait for 1 ns;
			
			b_i <= '1';
			wait for 1 ns;
			
			a_i <= '0';
			b_i <= '0';
			sel <= '1';
			wait for 1 ns;
	
			b_i <= '1';
			wait for 1 ns;
			
			a_i <= '1';
			b_i <= '0';
			wait for 1 ns;
			
			b_i <= '1';
			wait for 1 ns;
			
			wait;
		end process;
		end behavioural;

Elementary Gates/MuxWaveform.vcd
$date
  Mon Jul 20 20:27:59 2026
$end
$version
  GHDL v0
$end
$timescale
  1 fs
$end
$scope module standard $end
$upscope $end
$scope module std_logic_1164 $end
$upscope $end
$scope module mux_tb $end
$var reg 1 ! a_i $end
$var reg 1 " b_i $end
$var reg 1 # sel $end
$var reg 1 $ z_o $end
$scope module uut $end
$var reg 1 % a_i $end
$var reg 1 & b_i $end
$var reg 1 ' sel $end
$var reg 1 ( z_o $end
$var reg 1 ) sel_inv $end
$var reg 1 * st1_0 $end
$var reg 1 + st1_1 $end
$upscope $end
$upscope $end
$enddefinitions $end
#0
0!
0"
0#
0$
0%
0&
0'
0(
1)
1*
1+
#1000000
1"
1&
#2000000
1!
0"
1$
1%
0&
1(
0*
#3000000
1"
1&
#4000000
0!
0"
1#
0$
0%
0&
1'
0(
0)
1*
#5000000
1"
1$
1&
1(
0+
#6000000
1!
0"
0$
1%
0&
0(
1+
#7000000
1"
1$
1&
1(
0+
