Memory/ProgramCounter.vhdl
library ieee;
use ieee.std_logic_1164.all;
use ieee.numeric_std.all;

entity program_counter is
	port(
		clk : in std_logic;
		load : in std_logic;
		increment : in std_logic;
		reset : in std_logic;
		
		input : in std_logic_vector(15 downto 0);
		output : out std_logic_vector(15 downto 0)
		);
end program_counter;

architecture rtl of program_counter is

	signal pc_reg : std_logic_vector(15 downto 0);
	begin
	
	process (clk)
	begin
		if rising_edge(clk) then
			if reset = '1' then
				pc_reg <= x"0000";
			
			else if load = '1' then
				pc_reg <= input;
			
			else if increment = '1' then
				pc_reg <= std_logic_vector(unsigned(pc_reg) + 1);
				
			end if;
			end if;
			end if;
		end if;
		
		end process;
		
		output <= pc_reg;

end rtl;

Memory/ProgramCounterTB.vhdl
library ieee;
use ieee.std_logic_1164.all;
use ieee.numeric_std.all;

entity program_counter_tb is
end program_counter_tb;

architecture behavioural of program_counter_tb is

	signal clk, load, increment, reset : std_logic;
	signal input, output : std_logic_vector(15 downto 0);
	
	begin
	
		UUT : entity work.program_counter port map(
			clk => clk,
			load => load,
			increment => increment,
			reset => reset,
			
			input => input,
			output => output
			);
			
	clk_process : process
	begin
		clk <= '0';
		wait for 5 ns;
		clk <= '1';
		wait for 5 ns;
	end process;
	
	stimuli : process
	begin
		
		--test if load, increment and reset = 0 then nothing happens within the pc
		load <= '0';
		increment <= '0';
		reset <= '0';
		
		input <= x"1234";
		wait for 10 ns;
		
		--test if load = 1 then the input is loaded into the pc
		load <= '1';
		wait for 10 ns;
		
		--test if increment = 1 then pc increments
		load <= '0';
		increment <= '1';
		wait for 10 ns;
		
		--test if the pc can reset
		reset <= '1';
		increment <= '0';
		wait for 10 ns;
		
		--test new value can be loaded after reset
		reset <= '0';
		input <= x"349F";
		load <= '1';
		wait for 10 ns;
		
		wait;
	end process;
	
end behavioural;

Memory/ProgramCounterTBWaveform.vcd
$date
  Tue Jul 28 14:52:08 2026
$end
$version
  GHDL v0
$end
$timescale
  1 fs
$end
$scope module standard $end
$upscope $end
$scope module std_logic_1164 $end
$upscope $end
$scope module numeric_std $end
$upscope $end
$scope module program_counter_tb $end
$var reg 1 ! clk $end
$var reg 1 " load $end
$var reg 1 # increment $end
$var reg 1 $ reset $end
$var reg 16 % input[15:0] $end
$var reg 16 & output[15:0] $end
$scope module uut $end
$var reg 1 ' clk $end
$var reg 1 ( load $end
$var reg 1 ) increment $end
$var reg 1 * reset $end
$var reg 16 + input[15:0] $end
$var reg 16 , output[15:0] $end
$var reg 16 - pc_reg[15:0] $end
$upscope $end
$upscope $end
$enddefinitions $end
#0
0!
0"
0#
0$
b0001001000110100 %
bUUUUUUUUUUUUUUUU &
0'
0(
0)
0*
b0001001000110100 +
bUUUUUUUUUUUUUUUU ,
bUUUUUUUUUUUUUUUU -
#5000000
1!
1'
#10000000
0!
1"
0'
1(
#15000000
1!
b0001001000110100 &
1'
b0001001000110100 ,
b0001001000110100 -
#20000000
0!
0"
1#
0'
0(
1)
#25000000
1!
b0001001000110101 &
1'
b0001001000110101 ,
b0001001000110101 -
#30000000
0!
0#
1$
0'
0)
1*
#35000000
1!
b0000000000000000 &
1'
b0000000000000000 ,
b0000000000000000 -
#40000000
0!
1"
0$
b0011010010011111 %
0'
1(
0*
b0011010010011111 +
#45000000
1!
b0011010010011111 &
1'
b0011010010011111 ,
b0011010010011111 -
